ELLIPTIc-1.0.1.dist-info/METADATA
ELLIPTIc-1.0.1.dist-info/RECORD
ELLIPTIc-1.0.1.dist-info/WHEEL
ELLIPTIc-1.0.1.dist-info/top_level.txt
elliptic/__init__.py
elliptic/Kernel/Context.py
elliptic/Kernel/Contract.py
elliptic/Kernel/DSL.py
elliptic/Kernel/Expression.py
elliptic/Kernel/TemplateManager.py
elliptic/Kernel/TreeBuilder.py
elliptic/Kernel/__init__.py
examples/__init__.py
examples/DSL_Example/__init__.py
examples/DSL_Example/example.py
examples/DSL_Example/src/DSL.py
examples/DSL_Example/src/DSLImpl.py
examples/DSL_Example/src/__init__.py
