Metadata-Version: 2.1
Name: ELLIPTIc
Version: 1.0.1
Summary: A tool for building DSLs for scientific purposes.
Home-page: https://github.com/padmec-reservoir/ELLIPTIc
Author: Guilherme Caminha
Author-email: gpkc@cin.ufpe.br
License: MIT license
Platform: UNKNOWN
Classifier: Development Status :: 4 - Beta
Classifier: Intended Audience :: Developers
Classifier: License :: OSI Approved :: MIT License
Classifier: Natural Language :: English
Classifier: Programming Language :: Python :: 3
Classifier: Programming Language :: Python :: 3.6
Provides-Extra: docs
Requires-Dist: colorlog
Requires-Dist: configobj
Requires-Dist: anytree
Requires-Dist: typing-extensions
Requires-Dist: jinja2
Requires-Dist: cypyler
Provides-Extra: docs
Requires-Dist: sphinx; extra == 'docs'
Requires-Dist: sphinx-autodoc-typehints; extra == 'docs'
Requires-Dist: sphinx-rtd-theme; extra == 'docs'
